rtl/mips_cpu_statemac.v
module statemac(
    input logic halt,
    input logic waitrequest,
    input logic reset,
    input logic clk,
    output logic active,
    output logic f,
    output logic e1,
    output logic e2
);

parameter halt_state = 3'b000, fetch = 3'b001, exec1 = 3'b011, exec2 = 3'b101, stall_f = 3'b010, stall_e1 = 3'b100, stall_e2 = 3'b110;
reg [2:0] state = fetch;
/*
 if ((reset) && (state != halt_state)) begin
        state <= fetch;
    end
    else begin*/
always @(posedge clk) begin
        f = 0;
        e1 = 0;
        e2 = 0;
   
        case (state)

        fetch: begin
            $display("FSM: FETCH");
            active = 1;
            if (waitrequest) begin
                state <= stall_f;
            end
            else if (halt) begin
                state <= halt_state;
            end
            else if (reset) begin
                state <= fetch;
            end
            else begin
                state <= exec1;
            end
            f = 1;
        end

        exec1: begin
            $display("FSM: EXEC1");
            active = 1;
            if (waitrequest) begin
                state <= stall_e1;
            end
            else if (reset) begin
                state <= fetch;
            end
            else begin
                state <= exec2;
            end
            e1 = 1;
        end

        exec2: begin
            $display("FSM: EXEC2");
            active = 1;
            if (waitrequest) begin
                state <= stall_e2;
            end
            else begin
                state <= fetch;
            end
            e2 = 1; 
        end

        halt_state: begin
            $display("FSM: HALT");
            active = 0;
            if (reset) begin
                state <= fetch;
            end
            else begin
                state <= halt_state;
            end
        end

        stall_f: begin
            active = 1;
            if (!waitrequest) begin
                state <= fetch;
            end
            else begin
                state <= stall_f;
            end
        end

        stall_e1: begin
            active = 1;
            if (!waitrequest) begin
                state <= exec1;
            end
            else begin
                state <= stall_e1;
            end
        end

        stall_e2: begin
            active = 1;
            if (!waitrequest) begin
                state <= exec2;
            end
            else begin
                state <= stall_e2;
            end
        end


        endcase

    end


endmodule

rtl/mips_cpu_statemac_tb.v
module mips_cpu_statemac_tb ();
    logic halt;
    logic waitrequest;
    logic reset;
    logic clk;
    logic active;
    logic f;
    logic e1;
    logic e2;
    
    statemac fsm(
        .halt(halt),
        .waitrequest(waitrequest),
        .reset(reset),
        .clk(clk),
        .active(active),
        .f(f),
        .e1(e1),
        .e2(e2)
    );
    
    initial begin
        $dumpfile("mips_cpu_statemac_tb.vcd");
        $dumpvars(0, mips_cpu_statemac_tb);

        halt = 1;
        active = 0;
        waitrequest = 0;
        

        $display("Current State: f=%b, e1=%b, e2=%b", f, e1, e2);

        repeat(200) begin
            clk <= 0;
            #1;
            clk <= 1;
            #1;
        end

        #1
        halt = 0;
        #1;
        assert(active == 1); 

        #1;
        halt = 1;
        #1;
        assert(active == 0);

        
    end


endmodule

rtl/mips_cpu_statemac_tb.vcd
$date
	Thu Dec 16 16:32:34 2021
$end
$version
	Icarus Verilog
$end
$timescale
	1s
$end
$scope module mips_cpu_statemac_tb $end
$var wire 1 ! f $end
$var wire 1 " e2 $end
$var wire 1 # e1 $end
$var wire 1 $ active $end
$var reg 1 % clk $end
$var reg 1 & halt $end
$var reg 1 ' reset $end
$var reg 1 ( waitrequest $end
$scope module fsm $end
$var wire 1 % clk $end
$var wire 1 & halt $end
$var wire 1 ' reset $end
$var wire 1 ( waitrequest $end
$var reg 1 $ active $end
$var reg 1 # e1 $end
$var reg 1 " e2 $end
$var reg 1 ! f $end
$var reg 3 ) state [2:0] $end
$upscope $end
$upscope $end
$enddefinitions $end
#0
$dumpvars
b1 )
x(
x'
x&
0%
x$
x#
x"
x!
$end
#1
b11 )
1$
0"
0#
1!
1%
#2
0%
#3
b101 )
1#
0!
1%
#4
0%
#5
b1 )
1"
0#
1%
#6
0%
#7
b11 )
1!
0"
1%
#8
0%
#9
b101 )
1#
0!
1%
#10
0%
#11
b1 )
1"
0#
1%
#12
0%
#13
b11 )
1!
0"
1%
#14
0%
#15
b101 )
1#
0!
1%
#16
0%
#17
b1 )
1"
0#
1%
#18
0%
#19
b11 )
1!
0"
1%
#20
0%
#21
b101 )
1#
0!
1%
#22
0%
#23
b1 )
1"
0#
1%
#24
0%
#25
b11 )
1!
0"
1%
#26
0%
#27
b101 )
1#
0!
1%
#28
0%
#29
b1 )
1"
0#
1%
#30
0%
#31
b11 )
1!
0"
1%
#32
0%
#33
b101 )
1#
0!
1%
#34
0%
#35
b1 )
1"
0#
1%
#36
0%
#37
b11 )
1!
0"
1%
#38
0%
#39
b101 )
1#
0!
1%
#40
0%
#41
b1 )
1"
0#
1%
#42
0%
#43
b11 )
1!
0"
1%
#44
0%
#45
b101 )
1#
0!
1%
#46
0%
#47
b1 )
1"
0#
1%
#48
0%
#49
b11 )
1!
0"
1%
#50
0%
#51
b101 )
1#
0!
1%
#52
0%
#53
b1 )
1"
0#
1%
#54
0%
#55
b11 )
1!
0"
1%
#56
0%
#57
b101 )
1#
0!
1%
#58
0%
#59
b1 )
1"
0#
1%
#60
0%
#61
b11 )
1!
0"
1%
#62
0%
#63
b101 )
1#
0!
1%
#64
0%
#65
b1 )
1"
0#
1%
#66
0%
#67
b11 )
1!
0"
1%
#68
0%
#69
b101 )
1#
0!
1%
#70
0%
#71
b1 )
1"
0#
1%
#72
0%
#73
b11 )
1!
0"
1%
#74
0%
#75
b101 )
1#
0!
1%
#76
0%
#77
b1 )
1"
0#
1%
#78
0%
#79
b11 )
1!
0"
1%
#80
0%
#81
b101 )
1#
0!
1%
#82
0%
#83
b1 )
1"
0#
1%
#84
0%
#85
b11 )
1!
0"
1%
#86
0%
#87
b101 )
1#
0!
1%
#88
0%
#89
b1 )
1"
0#
1%
#90
0%
#91
b11 )
1!
0"
1%
#92
0%
#93
b101 )
1#
0!
1%
#94
0%
#95
b1 )
1"
0#
1%
#96
0%
#97
b11 )
1!
0"
1%
#98
0%
#99
b101 )
1#
0!
1%
#100
0%
#101
b1 )
1"
0#
1%
#102
0%
#103
b11 )
1!
0"
1%
#104
0%
#105
b101 )
1#
0!
1%
#106
0%
#107
b1 )
1"
0#
1%
#108
0%
#109
b11 )
1!
0"
1%
#110
0%
#111
b101 )
1#
0!
1%
#112
0%
#113
b1 )
1"
0#
1%
#114
0%
#115
b11 )
1!
0"
1%
#116
0%
#117
b101 )
1#
0!
1%
#118
0%
#119
b1 )
1"
0#
1%
#120
0%
#121
b11 )
1!
0"
1%
#122
0%
#123
b101 )
1#
0!
1%
#124
0%
#125
b1 )
1"
0#
1%
#126
0%
#127
b11 )
1!
0"
1%
#128
0%
#129
b101 )
1#
0!
1%
#130
0%
#131
b1 )
1"
0#
1%
#132
0%
#133
b11 )
1!
0"
1%
#134
0%
#135
b101 )
1#
0!
1%
#136
0%
#137
b1 )
1"
0#
1%
#138
0%
#139
b11 )
1!
0"
1%
#140
0%
#141
b101 )
1#
0!
1%
#142
0%
#143
b1 )
1"
0#
1%
#144
0%
#145
b11 )
1!
0"
1%
#146
0%
#147
b101 )
1#
0!
1%
#148
0%
#149
b1 )
1"
0#
1%
#150
0%
#151
b11 )
1!
0"
1%
#152
0%
#153
b101 )
1#
0!
1%
#154
0%
#155
b1 )
1"
0#
1%
#156
0%
#157
b11 )
1!
0"
1%
#158
0%
#159
b101 )
1#
0!
1%
#160
0%
#161
b1 )
1"
0#
1%
#162
0%
#163
b11 )
1!
0"
1%
#164
0%
#165
b101 )
1#
0!
1%
#166
0%
#167
b1 )
1"
0#
1%
#168
0%
#169
b11 )
1!
0"
1%
#170
0%
#171
b101 )
1#
0!
1%
#172
0%
#173
b1 )
1"
0#
1%
#174
0%
#175
b11 )
1!
0"
1%
#176
0%
#177
b101 )
1#
0!
1%
#178
0%
#179
b1 )
1"
0#
1%
#180
0%
#181
b11 )
1!
0"
1%
#182
0%
#183
b101 )
1#
0!
1%
#184
0%
#185
b1 )
1"
0#
1%
#186
0%
#187
b11 )
1!
0"
1%
#188
0%
#189
b101 )
1#
0!
1%
#190
0%
#191
b1 )
1"
0#
1%
#192
0%
#193
b11 )
1!
0"
1%
#194
0%
#195
b101 )
1#
0!
1%
#196
0%
#197
b1 )
1"
0#
1%
#198
0%
#199
b11 )
1!
0"
1%
#200
0%
#201
b101 )
1#
0!
1%
#202
0%
#203
b1 )
1"
0#
1%
#204
0%
#205
b11 )
1!
0"
1%
#206
0%
#207
b101 )
1#
0!
1%
#208
0%
#209
b1 )
1"
0#
1%
#210
0%
#211
b11 )
1!
0"
1%
#212
0%
#213
b101 )
1#
0!
1%
#214
0%
#215
b1 )
1"
0#
1%
#216
0%
#217
b11 )
1!
0"
1%
#218
0%
#219
b101 )
1#
0!
1%
#220
0%
#221
b1 )
1"
0#
1%
#222
0%
#223
b11 )
1!
0"
1%
#224
0%
#225
b101 )
1#
0!
1%
#226
0%
#227
b1 )
1"
0#
1%
#228
0%
#229
b11 )
1!
0"
1%
#230
0%
#231
b101 )
1#
0!
1%
#232
0%
#233
b1 )
1"
0#
1%
#234
0%
#235
b11 )
1!
0"
1%
#236
0%
#237
b101 )
1#
0!
1%
#238
0%
#239
b1 )
1"
0#
1%
#240
0%
#241
b11 )
1!
0"
1%
#242
0%
#243
b101 )
1#
0!
1%
#244
0%
#245
b1 )
1"
0#
1%
#246
0%
#247
b11 )
1!
0"
1%
#248
0%
#249
b101 )
1#
0!
1%
#250
0%
#251
b1 )
1"
0#
1%
#252
0%
#253
b11 )
1!
0"
1%
#254
0%
#255
b101 )
1#
0!
1%
#256
0%
#257
b1 )
1"
0#
1%
#258
0%
#259
b11 )
1!
0"
1%
#260
0%
#261
b101 )
1#
0!
1%
#262
0%
#263
b1 )
1"
0#
1%
#264
0%
#265
b11 )
1!
0"
1%
#266
0%
#267
b101 )
1#
0!
1%
#268
0%
#269
b1 )
1"
0#
1%
#270
0%
#271
b11 )
1!
0"
1%
#272
0%
#273
b101 )
1#
0!
1%
#274
0%
#275
b1 )
1"
0#
1%
#276
0%
#277
b11 )
1!
0"
1%
#278
0%
#279
b101 )
1#
0!
1%
#280
0%
#281
b1 )
1"
0#
1%
#282
0%
#283
b11 )
1!
0"
1%
#284
0%
#285
b101 )
1#
0!
1%
#286
0%
#287
b1 )
1"
0#
1%
#288
0%
#289
b11 )
1!
0"
1%
#290
0%
#291
b101 )
1#
0!
1%
#292
0%
#293
b1 )
1"
0#
1%
#294
0%
#295
b11 )
1!
0"
1%
#296
0%
#297
b101 )
1#
0!
1%
#298
0%
#299
b1 )
1"
0#
1%
#300
0%
#301
b11 )
1!
0"
1%
#302
0%
#303
b101 )
1#
0!
1%
#304
0%
#305
b1 )
1"
0#
1%
#306
0%
#307
b11 )
1!
0"
1%
#308
0%
#309
b101 )
1#
0!
1%
#310
0%
#311
b1 )
1"
0#
1%
#312
0%
#313
b11 )
1!
0"
1%
#314
0%
#315
b101 )
1#
0!
1%
#316
0%
#317
b1 )
1"
0#
1%
#318
0%
#319
b11 )
1!
0"
1%
#320
0%
#321
b101 )
1#
0!
1%
#322
0%
#323
b1 )
1"
0#
1%
#324
0%
#325
b11 )
1!
0"
1%
#326
0%
#327
b101 )
1#
0!
1%
#328
0%
#329
b1 )
1"
0#
1%
#330
0%
#331
b11 )
1!
0"
1%
#332
0%
#333
b101 )
1#
0!
1%
#334
0%
#335
b1 )
1"
0#
1%
#336
0%
#337
b11 )
1!
0"
1%
#338
0%
#339
b101 )
1#
0!
1%
#340
0%
#341
b1 )
1"
0#
1%
#342
0%
#343
b11 )
1!
0"
1%
#344
0%
#345
b101 )
1#
0!
1%
#346
0%
#347
b1 )
1"
0#
1%
#348
0%
#349
b11 )
1!
0"
1%
#350
0%
#351
b101 )
1#
0!
1%
#352
0%
#353
b1 )
1"
0#
1%
#354
0%
#355
b11 )
1!
0"
1%
#356
0%
#357
b101 )
1#
0!
1%
#358
0%
#359
b1 )
1"
0#
1%
#360
0%
#361
b11 )
1!
0"
1%
#362
0%
#363
b101 )
1#
0!
1%
#364
0%
#365
b1 )
1"
0#
1%
#366
0%
#367
b11 )
1!
0"
1%
#368
0%
#369
b101 )
1#
0!
1%
#370
0%
#371
b1 )
1"
0#
1%
#372
0%
#373
b11 )
1!
0"
1%
#374
0%
#375
b101 )
1#
0!
1%
#376
0%
#377
b1 )
1"
0#
1%
#378
0%
#379
b11 )
1!
0"
1%
#380
0%
#381
b101 )
1#
0!
1%
#382
0%
#383
b1 )
1"
0#
1%
#384
0%
#385
b11 )
1!
0"
1%
#386
0%
#387
b101 )
1#
0!
1%
#388
0%
#389
b1 )
1"
0#
1%
#390
0%
#391
b11 )
1!
0"
1%
#392
0%
#393
b101 )
1#
0!
1%
#394
0%
#395
b1 )
1"
0#
1%
#396
0%
#397
b11 )
1!
0"
1%
#398
0%
#399
b101 )
1#
0!
1%
